vnpy_paperaccount/__init__.py
vnpy_paperaccount/engine.py
vnpy_paperaccount/ui/__init__.py
vnpy_paperaccount/ui/paper.ico
vnpy_paperaccount/ui/widget.py
vnpy_paperaccount-1.0.6.dist-info/LICENSE
vnpy_paperaccount-1.0.6.dist-info/METADATA
vnpy_paperaccount-1.0.6.dist-info/WHEEL
vnpy_paperaccount-1.0.6.dist-info/top_level.txt
vnpy_paperaccount-1.0.6.dist-info/RECORD
